partial_table/__init__.py
partial_table/markers.py
partial_table/partial_table.py
partial_table-0.0.1a0.dist-info/LICENSE
partial_table-0.0.1a0.dist-info/METADATA
partial_table-0.0.1a0.dist-info/WHEEL
partial_table-0.0.1a0.dist-info/RECORD
