Metadata-Version: 2.3
Name: partial-table
Version: 0.0.1a0
Summary: Partial Table Models for SQLAlchemy
Author: Julien Kmec
Author-email: me@julien.dev
Requires-Python: >=3.10.0,<4.0.0
Classifier: Programming Language :: Python :: 3
Classifier: Programming Language :: Python :: 3.10
Classifier: Programming Language :: Python :: 3.11
Classifier: Programming Language :: Python :: 3.12
Classifier: Programming Language :: Python :: 3.13
Requires-Dist: psycopg2-binary (>=2.9.10,<3.0.0)
Requires-Dist: pytest (>=8.3.5,<9.0.0)
Requires-Dist: pytest-asyncio (>=0.26.0,<0.27.0)
Requires-Dist: pytest-docker (>=3.2.1,<4.0.0)
Requires-Dist: pytest-sqlalchemy (>=0.3.0,<0.4.0)
Requires-Dist: sqlalchemy (>=2.0.40,<3.0.0)
Requires-Dist: sqlalchemy-utils (>=0.41.2,<0.42.0)
Requires-Dist: sqlmodel (>=0.0.24,<0.0.25)
